setup.cfg
setup.py
Anar/All.py
Anar/Lagrange.py
Anar/__init__.py
Anar/brent.py
Anar/golden_ratio.py
Anar/gradient_descent_fixed.py
Anar/local_extrema.py
Anar/parabolic_interpolation.py
Anar/parse__restr_function.py
Anar/parse_restriction.py
Anar/parse_variables.py
Anar/parse_variables_tz2.py
Anar/parser_task.py
Anar/plot.py
Anar/plot_tz2.py
Anar/tz4.py
Anar.egg-info/PKG-INFO
Anar.egg-info/SOURCES.txt
Anar.egg-info/dependency_links.txt
Anar.egg-info/not-zip-safe
Anar.egg-info/top_level.txt