Metadata-Version: 2.1
Name: Anar
Version: 0.0.1.1.1.1.1.6
Summary: abc
Home-page: UNKNOWN
Author-email: anariem@mail.ru
License: UNKNOWN
Platform: UNKNOWN
